{
  "version": "7",
  "dialect": "sqlite",
  "entries": [
    {
      "idx": 0,
      "version": "6",
      "when": 1739302481687,
      "tag": "0000_blushing_captain_america",
      "breakpoints": true
    },
    {
      "idx": 1,
      "version": "6",
      "when": 1739359240246,
      "tag": "0001_burly_starjammers",
      "breakpoints": true
    },
    {
      "idx": 2,
      "version": "6",
      "when": 1739480390055,
      "tag": "0002_yellow_expediter",
      "breakpoints": true
    },
    {
      "idx": 3,
      "version": "6",
      "when": 1739482192856,
      "tag": "0003_old_tiger_shark",
      "breakpoints": true
    },
    {
      "idx": 4,
      "version": "6",
      "when": 1739953067926,
      "tag": "0004_aromatic_felicia_hardy",
      "breakpoints": true
    },
    {
      "idx": 5,
      "version": "6",
      "when": 1739953093840,
      "tag": "0005_lean_nightshade",
      "breakpoints": true
    },
    {
      "idx": 6,
      "version": "6",
      "when": 1739959746121,
      "tag": "0006_tranquil_vance_astro",
      "breakpoints": true
    },
    {
      "idx": 7,
      "version": "6",
      "when": 1739977010221,
      "tag": "0007_big_fenris",
      "breakpoints": true
    },
    {
      "idx": 8,
      "version": "6",
      "when": 1739977152698,
      "tag": "0008_freezing_korg",
      "breakpoints": true
    },
    {
      "idx": 9,
      "version": "6",
      "when": 1741339868698,
      "tag": "0009_remarkable_blur",
      "breakpoints": true
    },
    {
      "idx": 10,
      "version": "6",
      "when": 1741342102864,
      "tag": "0010_graceful_white_tiger",
      "breakpoints": true
    }
  ]
}